grep_excel/__init__.py
grep_excel/cli.py
grep_excel/grep.py
grep_excel-1.0.0.dist-info/LICENSE
grep_excel-1.0.0.dist-info/METADATA
grep_excel-1.0.0.dist-info/WHEEL
grep_excel-1.0.0.dist-info/entry_points.txt
grep_excel-1.0.0.dist-info/top_level.txt
grep_excel-1.0.0.dist-info/RECORD
