Metadata-Version: 2.1
Name: grep_excel
Version: 1.0.0
Summary: A grep-like utility for searching Excel files
Home-page: https://github.com/stenzr/grep_excel
Author: Rohit Kumar
Author-email: rkrohitkr01@gmail.com
License: MIT
Requires-Python: >=3.6
License-File: LICENSE
Requires-Dist: setuptools ==71.1.0
Requires-Dist: bump2version ==1.0.1
Requires-Dist: bumpversion ==0.6.0
Requires-Dist: pandas ==2.2.2
Requires-Dist: twine ==5.1.1
Provides-Extra: test
Requires-Dist: unittest ; extra == 'test'
Requires-Dist: coverage ; extra == 'test'
